Metadata-Version: 2.1
Name: DeFiPi
Version: 0.0.1
Summary: DeFiPi
Home-page: http://github.com/icmoore/defipi
Author: icmoore
Author-email: defipy.devs@gmail.com
License: MIT
Platform: UNKNOWN
License-File: LICENSE.txt
